infi.parted-0.2.20-py3.7-nspkg.pth
infi/parted/__init__.py
infi/parted/__version__.py
infi/parted/tests/__init__.py
infi.parted-0.2.20.dist-info/LICENSE
infi.parted-0.2.20.dist-info/METADATA
infi.parted-0.2.20.dist-info/WHEEL
infi.parted-0.2.20.dist-info/entry_points.txt
infi.parted-0.2.20.dist-info/namespace_packages.txt
infi.parted-0.2.20.dist-info/top_level.txt
infi.parted-0.2.20.dist-info/RECORD
