Metadata-Version: 2.1
Name: infi.parted
Version: 0.2.20
Summary: Python library for adding/removing disk partitions in linux
Home-page: https://github.com/Infinidat/infi.parted
Author: Arnon Yaari
Author-email: arnony@infinidat.com
License: BSD
Platform: UNKNOWN
Classifier: Intended Audience :: Developers
Classifier: Intended Audience :: System Administrators
Classifier: License :: OSI Approved :: BSD License
Classifier: Operating System :: OS Independent
Classifier: Programming Language :: Python
Classifier: Programming Language :: Python :: 2
Classifier: Programming Language :: Python :: 3
Classifier: Topic :: Software Development :: Libraries :: Python Modules
Requires-Dist: capacity
Requires-Dist: distro
Requires-Dist: infi.exceptools
Requires-Dist: infi.execute
Requires-Dist: infi.pyutils
Requires-Dist: setuptools
